xbrluspy/__init__.py
xbrluspy/models.py
xbrluspy-0.0.1.dist-info/LICENSE
xbrluspy-0.0.1.dist-info/METADATA
xbrluspy-0.0.1.dist-info/WHEEL
xbrluspy-0.0.1.dist-info/top_level.txt
xbrluspy-0.0.1.dist-info/RECORD
