Metadata-Version: 2.1
Name: xbrluspy
Version: 0.0.1
Summary: An API wrapper for making requests to the XBRL.US Data filings API
Author-email: "Ihab P." <hcyip42@gmail.com>
Project-URL: Homepage, https://github.com/ITP2023/xbrluspy
Project-URL: Issues, https://github.com/ITP2023/xbrluspy/issues
Classifier: Programming Language :: Python :: 3
Classifier: License :: OSI Approved :: MIT License
Classifier: Operating System :: OS Independent
Requires-Python: >=3.8
License-File: LICENSE
Requires-Dist: requests
